HslCommunication/__init__.py
HslCommunication-1.0.4.dist-info/LICENSE
HslCommunication-1.0.4.dist-info/METADATA
HslCommunication-1.0.4.dist-info/WHEEL
HslCommunication-1.0.4.dist-info/top_level.txt
HslCommunication-1.0.4.dist-info/RECORD
