Metadata-Version: 2.1
Name: HslCommunication
Version: 1.0.4
Summary: An industrial IoT underlying architecture framework, focusing on the underlying technical communications.
Home-page: https://github.com/dathlin/HslCommunication
Author: Richard.Hu
Author-email: hsl200909@163.com
License: UNKNOWN
Platform: UNKNOWN
Classifier: Programming Language :: Python :: 3
Classifier: License :: OSI Approved :: MIT License
Classifier: Operating System :: OS Independent
Requires-Python: >=3.5
